protview/ProtView.py
protview/__init__.py
protview/cds_extraction_args.py
protview/cds_extraction_main.py
protview/fasta_input_sanitation_args.py
protview/fasta_input_sanitation_main.py
protview/gen_coords_args.py
protview/gen_coords_main.py
protview/junction_peptides_args.py
protview/junction_peptides_main.py
protview/junction_summary_args.py
protview/junction_summary_main.py
protview/rpg_output_processing_args.py
protview/rpg_output_processing_main.py
protview/setup_commands_args.py
protview/setup_commands_main.py
protview/summary_stats_args.py
protview/summary_stats_main.py
protview/unique_count_args.py
protview/unique_count_main.py
protview-1.0.5.dist-info/LICENSE
protview-1.0.5.dist-info/METADATA
protview-1.0.5.dist-info/WHEEL
protview-1.0.5.dist-info/entry_points.txt
protview-1.0.5.dist-info/top_level.txt
protview-1.0.5.dist-info/RECORD
