Metadata-Version: 2.1
Name: protview
Version: 1.0.5
Summary: Digest scheme evaluation in proteomic & proteogenomic context
Home-page: https://github.com/SSPuliasis/ProtView
Author: Sophia Puliasis
Author-email: SSPuliasis@dundee.ac.uk
License: GPL v3
Platform: UNKNOWN
Requires-Python: >=3.8
Requires-Dist: numpy
Requires-Dist: pandas
Requires-Dist: gffpandas
Requires-Dist: BioPython
Requires-Dist: rpg
Requires-Dist: pexpect
